apiverve_htmltopdf/__init__.py
apiverve_htmltopdf/apiClient.py
apiverve_htmltopdf/exceptions.py
apiverve_htmltopdf/setup.py
apiverve_htmltopdf/setup_dep.py
apiverve_htmltopdf/tests/__init__.py
apiverve_htmltopdf/tests/test_api.py
apiverve_htmltopdf-1.1.5.dist-info/LICENSE
apiverve_htmltopdf-1.1.5.dist-info/METADATA
apiverve_htmltopdf-1.1.5.dist-info/WHEEL
apiverve_htmltopdf-1.1.5.dist-info/top_level.txt
apiverve_htmltopdf-1.1.5.dist-info/RECORD
